{"containers":{"firefox-container-1":{"id":"firefox-container-1","cookieStoreId":"firefox-container-1","name":"Issue Ops","icon":"circle","color":"blue","colorCode":"#37adff","proxified":false,"proxy":null,"reopenRulesActive":false,"reopenRules":[],"userAgentActive":false,"userAgent":""},"firefox-container-2":{"id":"firefox-container-2","cookieStoreId":"firefox-container-2","name":"Migration Portal","icon":"circle","color":"orange","colorCode":"#37adff","proxified":false,"proxy":null,"reopenRulesActive":false,"reopenRules":[],"userAgentActive":false,"userAgent":""},"firefox-container-3":{"id":"firefox-container-3","cookieStoreId":"firefox-container-3","name":"Webhooks","icon":"circle","color":"green","colorCode":"#37adff","proxified":false,"proxy":null,"reopenRulesActive":false,"reopenRules":[],"userAgentActive":false,"userAgent":""},"firefox-container-8":{"id":"firefox-container-8","cookieStoreId":"firefox-container-8","name":"TAP Console","icon":"circle","color":"red","colorCode":"#37adff","proxified":false,"proxy":null,"reopenRulesActive":false,"reopenRules":[],"userAgentActive":false,"userAgent":""},"firefox-container-9":{"id":"firefox-container-9","cookieStoreId":"firefox-container-9","name":"Misc","icon":"circle","color":"purple","colorCode":"#37adff","proxified":false,"proxy":null,"reopenRulesActive":false,"reopenRules":[],"userAgentActive":false,"userAgent":""}},"settings":{"nativeScrollbars":true,"nativeScrollbarsThin":true,"nativeScrollbarsLeft":false,"selWinScreenshots":false,"updateSidebarTitle":true,"markWindow":false,"markWindowPreface":"[Sidebery] ","ctxMenuNative":false,"ctxMenuRenderInact":true,"ctxMenuRenderIcons":true,"ctxMenuIgnoreContainers":"","navBarLayout":"horizontal","navBarInline":true,"navBarSide":"right","hideAddBtn":false,"hideSettingsBtn":false,"navBtnCount":true,"hideEmptyPanels":true,"hideDiscardedTabPanels":false,"navActTabsPanelLeftClickAction":"none","navActBookmarksPanelLeftClickAction":"none","navTabsPanelMidClickAction":"discard","navBookmarksPanelMidClickAction":"none","navSwitchPanelsWheel":true,"subPanelRecentlyClosedBar":false,"subPanelBookmarks":false,"subPanelHistory":false,"subPanelSync":false,"groupLayout":"list","containersSortByName":true,"skipEmptyPanels":false,"dndTabAct":true,"dndTabActDelay":750,"dndTabActMod":"none","dndExp":"pointer","dndExpDelay":750,"dndExpMod":"none","dndOutside":"win","dndActTabFromLink":true,"dndActSearchTab":true,"dndMoveTabs":false,"dndMoveBookmarks":false,"searchBarMode":"dynamic","searchPanelSwitch":"same_type","searchBookmarksShortcut":"","searchHistoryShortcut":"","warnOnMultiTabClose":"collapsed","activateLastTabOnPanelSwitching":true,"activateLastTabOnPanelSwitchingLoadedOnly":true,"switchPanelAfterSwitchingTab":"always","tabRmBtn":"hover","activateAfterClosing":"next","activateAfterClosingStayInPanel":false,"activateAfterClosingGlobal":false,"activateAfterClosingNoFolded":true,"activateAfterClosingNoDiscarded":true,"askNewBookmarkPlace":true,"tabsRmUndoNote":true,"tabsUnreadMark":false,"tabsUpdateMark":"all","tabsUpdateMarkFirst":true,"tabsReloadLimit":5,"tabsReloadLimitNotif":true,"showNewTabBtns":true,"newTabBarPosition":"bottom","tabsPanelSwitchActMove":true,"tabsPanelSwitchActMoveAuto":false,"tabsUrlInTooltip":"full","newTabCtxReopen":true,"tabWarmupOnHover":true,"tabSwitchDelay":0,"forceDiscard":true,"moveNewTabPin":"end","moveNewTabParent":"last_child","moveNewTabParentActPanel":false,"moveNewTab":"none","moveNewTabActivePin":"end","pinnedTabsPosition":"panel","pinnedTabsList":false,"pinnedAutoGroup":false,"pinnedNoUnload":false,"pinnedForcedDiscard":false,"tabsTree":true,"groupOnOpen":true,"tabsTreeLimit":"none","autoFoldTabs":false,"autoFoldTabsExcept":"none","autoExpandTabs":false,"autoExpandTabsOnNew":false,"rmChildTabs":"folded","tabsLvlDots":true,"discardFolded":false,"discardFoldedDelay":0,"discardFoldedDelayUnit":"sec","tabsTreeBookmarks":true,"treeRmOutdent":"branch","autoGroupOnClose":true,"autoGroupOnClose0Lvl":true,"autoGroupOnCloseMouseOnly":true,"ignoreFoldedParent":false,"showNewGroupConf":true,"sortGroupsFirst":true,"colorizeTabs":true,"colorizeTabsSrc":"container","colorizeTabsBranches":false,"colorizeTabsBranchesSrc":"url","inheritCustomColor":true,"previewTabs":true,"previewTabsMode":"p","previewTabsPageModeFallback":"n","previewTabsInlineHeight":70,"previewTabsPopupWidth":280,"previewTabsTitle":2,"previewTabsUrl":1,"previewTabsSide":"right","previewTabsDelay":500,"previewTabsFollowMouse":true,"previewTabsWinOffsetY":36,"previewTabsWinOffsetX":6,"previewTabsInPageOffsetY":0,"previewTabsInPageOffsetX":0,"previewTabsCropRight":0,"hideInact":false,"hideFoldedTabs":false,"hideFoldedParent":"none","nativeHighlight":true,"warnOnMultiBookmarkDelete":"collapsed","autoCloseBookmarks":false,"autoRemoveOther":false,"highlightOpenBookmarks":false,"activateOpenBookmarkTab":false,"showBookmarkLen":true,"bookmarksRmUndoNote":true,"loadBookmarksOnDemand":true,"pinOpenedBookmarksFolder":true,"oldBookmarksAfterSave":"ask","loadHistoryOnDemand":true,"fontSize":"m","animations":true,"animationSpeed":"norm","theme":"proton","density":"compact","colorScheme":"ff","snapNotify":true,"snapExcludePrivate":false,"snapInterval":15,"snapIntervalUnit":"min","snapLimit":0,"snapLimitUnit":"snap","snapAutoExport":true,"snapAutoExportType":"json","snapAutoExportPath":"firefox/Sidebery/snapshot-%Y.%M.%D-%h.%m.%s","snapMdFullTree":true,"hScrollAction":"none","onePanelSwitchPerScroll":false,"wheelAccumulationX":true,"wheelAccumulationY":true,"navSwitchPanelsDelay":128,"scrollThroughTabs":"none","scrollThroughVisibleTabs":true,"scrollThroughTabsSkipDiscarded":true,"scrollThroughTabsExceptOverflow":true,"scrollThroughTabsCyclic":false,"scrollThroughTabsScrollArea":0,"autoMenuMultiSel":true,"multipleMiddleClose":false,"longClickDelay":500,"wheelThreshold":false,"wheelThresholdX":10,"wheelThresholdY":60,"tabDoubleClick":"none","tabsSecondClickActPrev":false,"tabsSecondClickActPrevPanelOnly":false,"tabsSecondClickActPrevNoUnload":false,"shiftSelAct":true,"activateOnMouseUp":false,"tabLongLeftClick":"none","tabLongRightClick":"none","tabMiddleClick":"close","tabPinnedMiddleClick":"discard","tabMiddleClickCtrl":"discard","tabMiddleClickShift":"duplicate","tabCloseMiddleClick":"close","tabsPanelLeftClickAction":"none","tabsPanelDoubleClickAction":"tab","tabsPanelRightClickAction":"menu","tabsPanelMiddleClickAction":"tab","newTabMiddleClickAction":"new_child","bookmarksLeftClickAction":"open_in_act","bookmarksLeftClickActivate":false,"bookmarksLeftClickPos":"default","bookmarksMidClickAction":"open_in_new","bookmarksMidClickActivate":false,"bookmarksMidClickRemove":false,"bookmarksMidClickPos":"default","historyLeftClickAction":"open_in_act","historyLeftClickActivate":false,"historyLeftClickPos":"default","historyMidClickAction":"open_in_new","historyMidClickActivate":false,"historyMidClickPos":"default","syncName":"plyr4","syncUseFirefox":true,"syncUseGoogleDrive":false,"syncUseGoogleDriveApi":false,"syncUseGoogleDriveApiClientId":"","syncSaveSettings":false,"syncSaveCtxMenu":false,"syncSaveStyles":false,"syncSaveKeybindings":false,"selectActiveTabFirst":true,"selectCyclic":false},"ver":"5.3.2","keybindings":{"_execute_sidebar_action":"MacCtrl+E","next_panel":"Alt+Period","prev_panel":"Alt+Comma","new_tab_on_panel":"MacCtrl+Space","new_tab_in_group":"MacCtrl+Shift+Space","up":"Alt+Up","down":"Alt+Down","up_shift":"Alt+Shift+Up","down_shift":"Alt+Shift+Down","activate":"Alt+Space","reset_selection":"Alt+R"}}